README.md
setup.py
leopard/__init__.py
leopard/config.py
leopard/utils.py
leopard.egg-info/PKG-INFO
leopard.egg-info/SOURCES.txt
leopard.egg-info/dependency_links.txt
leopard.egg-info/not-zip-safe
leopard.egg-info/requires.txt
leopard.egg-info/top_level.txt
leopard/extensions/__init__.py
leopard/extensions/latex.py