Metadata-Version: 2.1
Name: leopard
Version: 0.2.6
Summary: Fast lab reporting python package
Home-page: https://github.com/beukueb/leopard
Author: Christophe Van Neste
Author-email: christophe.vanneste@ugent.be
License: MIT
Platform: UNKNOWN
Provides-Extra: documentation
